proton/__init__.py
proton/_ctsrp.py
proton/_pysrp.py
proton/client.py
proton/constants.py
proton/helpers.py
proton/login.py
proton_api_client-0.0.8.dist-info/LICENSE
proton_api_client-0.0.8.dist-info/METADATA
proton_api_client-0.0.8.dist-info/WHEEL
proton_api_client-0.0.8.dist-info/top_level.txt
proton_api_client-0.0.8.dist-info/RECORD
