Metadata-Version: 2.1
Name: proton-api-client
Version: 0.0.8
Summary: Proton Mail API
Home-page: https://github.com/trevorhobenshield/proton-api-client
Author: Trevor Hobenshield
Author-email: trevorhobenshield@gmail.com
Keywords: proton api client async search automation bot scrape mail email
Requires-Python: >=3.10.10
License-File: LICENSE
Requires-Dist: bcrypt
Requires-Dist: python-gnupg
Requires-Dist: pyopenssl
Requires-Dist: selectolax
Requires-Dist: orjson
Requires-Dist: httpx
Requires-Dist: tqdm
Requires-Dist: nest-asyncio
Requires-Dist: uvloop ; platform_system != "Windows"
